nakama/__init__.py
nakama-0.1.0.dist-info/WHEEL
nakama-0.1.0.dist-info/METADATA
nakama-0.1.0.dist-info/RECORD
