Metadata-Version: 2.1
Name: nakama
Version: 0.1.0
Summary: Python client for nakama server
License: MIT
Author: Felipe Ruhland
Author-email: felipe.ruhland@gmail.com
Requires-Python: >=3.9,<4.0
Classifier: License :: OSI Approved :: MIT License
Classifier: Programming Language :: Python :: 3
